{"cameraMode":{"drawMode":0,"name":"Shaded","section":"Shading Mode"},"sceneLighting":true,"audioPlay":false,"sceneViewState":{"showFog":true,"showMaterialUpdate":false,"showSkybox":true,"showFlares":true,"showImageEffects":true,"showParticleSystems":true},"in2DMode":false,"pivot":{"x":-12.074663162231446,"y":-3.6067447662353517,"z":3.1683731079101564},"rotation":{"x":0.18843361735343934,"y":-0.5395730137825012,"z":0.12537458539009095,"w":0.8109469413757324},"size":41.18340301513672,"orthographic":false}